{
  "standings": [
    { "team": "Титан", "played": 6, "wins": 6, "draws": 0, "losses": 0, "goalsFor": 71, "goalsAgainst": 15, "points": 18 },
    { "team": "Микрон", "played": 6, "wins": 4, "draws": 0, "losses": 2, "goalsFor": 18, "goalsAgainst": 12, "points": 12 },
    { "team": "Луки-энергия-2", "played": 6, "wins": 3, "draws": 1, "losses": 2, "goalsFor": 15, "goalsAgainst": 11, "points": 10 },
    { "team": "Стрела", "played": 6, "wins": 2, "draws": 2, "losses": 2, "goalsFor": 10, "goalsAgainst": 10, "points": 8 },
    { "team": "Металлист", "played": 6, "wins": 2, "draws": 0, "losses": 4, "goalsFor": 9, "goalsAgainst": 17, "points": 6 },
    { "team": "Опочка", "played": 6, "wins": 0, "draws": 0, "losses": 6, "goalsFor": 5, "goalsAgainst": 21, "points": 0 }
  ],
  "matches": [
    {
      "id": 1,
      "tour": 1,
      "date": "2026-06-01",
      "time": "18:00",
      "homeTeam": "Титан",
      "awayTeam": "Микрон",
      "homeScore": 11,
      "awayScore": 2,
      "stadium": "Экспресс",
      "status": "finished",
      "events": [
        { "minute": 1, "player": "Андрей Науменко", "team": "Титан", "type": "goal", "assist": "Леха Савицкий" },
        { "minute": 34, "player": "Алексей Морозов", "team": "Спарта", "type": "goal" },
        { "minute": 45, "player": "Сергей Смирнов", "team": "Олимп", "type": "goal", "assist": "Иван Петров" },
        { "minute": 67, "player": "Иван Петров", "team": "Олимп", "type": "goal", "assist": "Андрей Волков" },
        { "minute": 55, "player": "Дмитрий Козлов", "team": "Вулкан", "type": "yellowCard" }
      ],
      "lineups": {
        "home": ["Савицкий А.", "Ткачев Ю.", "Науменко А.", "Лютер В.", "Козлов А."],
        "away": ["Алексей Морозов", "Олег Кузнецов", "Николай Зайцев", "Павел Громов", "Сергей Фёдоров"]
      }
    },
    {
      "id": 2,
      "tour": 1,
      "date": "2026-06-01",
      "time": "19:30",
      "homeTeam": "Вулкан",
      "awayTeam": "Динамо",
      "homeScore": 4,
      "awayScore": 2,
      "stadium": "Центральный",
      "status": "finished",
      "events": [],
      "lineups": { "home": [], "away": [] }
    },
    {
      "id": 3,
      "tour": 2,
      "date": "2026-06-03",
      "time": "20:00",
      "homeTeam": "Торнадо",
      "awayTeam": "Локомотив",
      "homeScore": 5,
      "awayScore": 0,
      "stadium": "Юность",
      "status": "finished",
      "events": [],
      "lineups": { "home": [], "away": [] }
    },
    {
      "id": 4,
      "tour": 2,
      "date": "2026-06-04",
      "time": "17:00",
      "homeTeam": "Динамо",
      "awayTeam": "Олимп",
      "homeScore": 1,
      "awayScore": 6,
      "stadium": "Центральный",
      "status": "finished",
      "events": [],
      "lineups": { "home": [], "away": [] }
    },
    {
      "id": 5,
      "tour": 3,
      "date": "2026-06-05",
      "time": "19:00",
      "homeTeam": "Спарта",
      "awayTeam": "Вулкан",
      "homeScore": 2,
      "awayScore": 2,
      "stadium": "Юность",
      "status": "live",
      "events": [
        { "minute": 5, "player": "Алексей Морозов", "team": "Спарта", "type": "goal" },
        { "minute": 38, "player": "Дмитрий Козлов", "team": "Вулкан", "type": "goal", "assist": "Игорь Лавров" },
        { "minute": 44, "player": "Алексей Морозов", "team": "Спарта", "type": "goal" },
        { "minute": 52, "player": "Игорь Лавров", "team": "Вулкан", "type": "goal" }
      ],
      "lineups": {
        "home": ["Алексей Морозов", "Олег Кузнецов", "Николай Зайцев"],
        "away": ["Дмитрий Козлов", "Игорь Лавров", "Павел Громов"]
      }
    },
    {
      "id": 6,
      "tour": 3,
      "date": "2026-06-06",
      "time": "16:00",
      "homeTeam": "Локомотив",
      "awayTeam": "Торнадо",
      "homeScore": 1,
      "awayScore": 3,
      "stadium": "Центральный",
      "status": "finished",
      "events": [],
      "lineups": { "home": [], "away": [] }
    },
    {
      "id": 7,
      "tour": 4,
      "date": "2026-06-10",
      "time": "18:00",
      "homeTeam": "Олимп",
      "awayTeam": "Вулкан",
      "homeScore": null,
      "awayScore": null,
      "stadium": "Центральный",
      "status": "upcoming",
      "events": [],
      "lineups": { "home": [], "away": [] }
    }
  ],
  "players": [
    { "name": "Иван Петров", "team": "Олимп", "number": 10, "goals": 7, "assists": 3, "yellowCards": 1, "redCards": 0 },
    { "name": "Сергей Смирнов", "team": "Олимп", "number": 7, "goals": 4, "assists": 5, "yellowCards": 0, "redCards": 0 },
    { "name": "Андрей Волков", "team": "Торнадо", "number": 11, "goals": 6, "assists": 2, "yellowCards": 2, "redCards": 0 },
    { "name": "Дмитрий Козлов", "team": "Вулкан", "number": 9, "goals": 5, "assists": 4, "yellowCards": 1, "redCards": 1 },
    { "name": "Алексей Морозов", "team": "Спарта", "number": 8, "goals": 2, "assists": 1, "yellowCards": 3, "redCards": 0 }
  ],
  "teams": [
    { "name": "Олимп", "coach": "Виктор Сидоров" },
    { "name": "Торнадо", "coach": "Павел Громов" },
    { "name": "Вулкан", "coach": "Игорь Лавров" },
    { "name": "Спарта", "coach": "Олег Кузнецов" },
    { "name": "Динамо", "coach": "Сергей Фёдоров" },
    { "name": "Локомотив", "coach": "Николай Зайцев" }
  ]
}
